shushpy/__init__.py
shushpy/__main__.py
shushpy/cli.py
shushpy-0.0.1.dev5.dist-info/METADATA
shushpy-0.0.1.dev5.dist-info/WHEEL
shushpy-0.0.1.dev5.dist-info/entry_points.txt
shushpy-0.0.1.dev5.dist-info/licenses/LICENSE.md
shushpy-0.0.1.dev5.dist-info/RECORD
