Metadata-Version: 2.4
Name: shushpy
Version: 0.0.1.dev5
Summary: Remove all comments and docstrings from Python code using a safe AST-based transform.
Project-URL: Homepage, https://pypi.org/project/shushpy/
Author: vodkar
License: MIT License
License-File: LICENSE.md
Classifier: Development Status :: 4 - Beta
Classifier: Intended Audience :: Developers
Classifier: License :: OSI Approved :: MIT License
Classifier: Operating System :: OS Independent
Classifier: Programming Language :: Python
Classifier: Programming Language :: Python :: 3
Classifier: Programming Language :: Python :: 3 :: Only
Classifier: Programming Language :: Python :: 3.12
Classifier: Topic :: Software Development :: Libraries
Classifier: Topic :: Utilities
Classifier: Typing :: Typed
Requires-Python: >=3.12
